pyshac/__init__.py
pyshac/config/__init__.py
pyshac/config/callbacks.py
pyshac/config/data.py
pyshac/config/hyperparameters.py
pyshac/core/__init__.py
pyshac/core/engine.py
pyshac/core/managed/__init__.py
pyshac/core/managed/keras_engine.py
pyshac/core/managed/tf_engine.py
pyshac/core/managed/torch_engine.py
pyshac/utils/__init__.py
pyshac/utils/vis_utils.py
pyshac/utils/xgb_utils.py
tests/__init__.py
pyshac-0.3.5.1.dist-info/LICENSE
pyshac-0.3.5.1.dist-info/METADATA
pyshac-0.3.5.1.dist-info/WHEEL
pyshac-0.3.5.1.dist-info/top_level.txt
pyshac-0.3.5.1.dist-info/RECORD
